setup.py
sendgrid_newsletter.egg-info/PKG-INFO
sendgrid_newsletter.egg-info/SOURCES.txt
sendgrid_newsletter.egg-info/dependency_links.txt
sendgrid_newsletter.egg-info/requires.txt
sendgrid_newsletter.egg-info/top_level.txt
sendgridnewsletter/__init__.py
sendgridnewsletter/base.py
sendgridnewsletter/client.py
sendgridnewsletter/exceptions.py
sendgridnewsletter/identities.py
sendgridnewsletter/lists.py
sendgridnewsletter/newsletters.py
sendgridnewsletter/recipients.py
sendgridnewsletter/schedules.py