Metadata-Version: 1.1
Name: sendgrid-newsletter
Version: 0.1.1
Summary: Library for using SendGrids newsletter api
Home-page: https://github.com/ConsumerAffairs/sendgrid-newsletter
Author: Buddy Lindsey, Jr.
Author-email: blindsey@consumeraffairs.com
License: UNKNOWN
Platform: UNKNOWN
Classifier: Development Status :: 3 - Alpha
Classifier: Intended Audience :: Developers
Classifier: License :: OSI Approved :: MIT License
Classifier: Programming Language :: Python
Classifier: Programming Language :: Python :: 2.7
Classifier: Topic :: Communications :: Email
